corenlp_pywrap/__init__.py
corenlp_pywrap/example.py
corenlp_pywrap/pywrap.py
corenlp_pywrap/test_using_pytest.py
corenlp_pywrap-1.0.5.dist-info/DESCRIPTION.rst
corenlp_pywrap-1.0.5.dist-info/METADATA
corenlp_pywrap-1.0.5.dist-info/RECORD
corenlp_pywrap-1.0.5.dist-info/WHEEL
corenlp_pywrap-1.0.5.dist-info/metadata.json
corenlp_pywrap-1.0.5.dist-info/top_level.txt
