Metadata-Version: 1.1
Name: corenlp-pywrap
Version: 1.0.5
Summary: A powerful python wraper for Stanford CoreNLP
Home-page: https://www.github.com/hhsecond/corenlp_pywrap
Author: hhsecond
Author-email: sherinct@live.com
License: MIT
Download-URL: https://www.github.com/hhsecond/corenlp_pywrap/tarball/1.0.5
Keywords: stanford corenlp wrapper
Platform: UNKNOWN
Classifier: Development Status :: 5 - Production/Stable
Classifier: Intended Audience :: Science/Research
Classifier: Topic :: Scientific/Engineering :: Artificial Intelligence
Classifier: License :: OSI Approved :: MIT License
